llamazure/rbac/__init__.py
llamazure/rbac/repository.py
llamazure/rbac/resources.py
llamazure/rbac/roles.py
llamazure/rbac/authorization/r/m/authorization/RoleAssignments.py
llamazure/rbac/authorization/r/m/authorization/RoleDefinitions.py
llamazure/rbac/authorization/r/m/authorization/common_types.py
llamazure/rbac/c/r/v2/types.py
llamazure.rbac-0.2.0.dist-info/METADATA
llamazure.rbac-0.2.0.dist-info/WHEEL
llamazure.rbac-0.2.0.dist-info/namespace_packages.txt
llamazure.rbac-0.2.0.dist-info/top_level.txt
llamazure.rbac-0.2.0.dist-info/RECORD
