Metadata-Version: 2.1
Name: llamazure.rbac
Version: 0.2.0
Summary: Azure roles, users, and assignments
Author: Daniel Goldman
License: Round Robin 2.0.0
Classifier: Development Status :: 3 - Alpha
Classifier: Programming Language :: Python :: 3.9
Classifier: Programming Language :: Python :: 3.10
Classifier: Programming Language :: Python :: 3.11
Classifier: Programming Language :: Python :: 3.12
Classifier: Programming Language :: Python :: 3.13
Classifier: Topic :: Utilities
Classifier: Topic :: Internet :: Log Analysis
Requires-Python: >=3.9
Requires-Dist: llamazure.azrest (~=0.3.0)
Requires-Dist: llamazure.msgraph (~=0.1.0)
Requires-Dist: llamazure.rid (~=0.1.0)
